netcdf_meta.py
netcdf_meta-1.0.2.dist-info/METADATA
netcdf_meta-1.0.2.dist-info/WHEEL
netcdf_meta-1.0.2.dist-info/entry_points.txt
netcdf_meta-1.0.2.dist-info/top_level.txt
netcdf_meta-1.0.2.dist-info/RECORD
