Metadata-Version: 2.1
Name: netcdf-meta
Version: 1.0.2
Requires-Dist: netCDF4
